forge_sdk/__init__.py
forge_sdk/forge_conn.py
forge_sdk/config/__init__.py
forge_sdk/config/config.py
forge_sdk/did/__init__.py
forge_sdk/did/abt_did.py
forge_sdk/did/auth.py
forge_sdk/did/lib.py
forge_sdk/mcrypto/__init__.py
forge_sdk/mcrypto/hasher.py
forge_sdk/mcrypto/signer.py
forge_sdk/protos/__init__.py
forge_sdk/protos/protos/__init__.py
forge_sdk/protos/protos/account_migrate_pb2.py
forge_sdk/protos/protos/account_migrate_pb2_grpc.py
forge_sdk/protos/protos/acquire_asset_pb2.py
forge_sdk/protos/protos/acquire_asset_pb2_grpc.py
forge_sdk/protos/protos/activate_protocol_pb2.py
forge_sdk/protos/protos/activate_protocol_pb2_grpc.py
forge_sdk/protos/protos/approve_withdraw_pb2.py
forge_sdk/protos/protos/approve_withdraw_pb2_grpc.py
forge_sdk/protos/protos/consume_asset_pb2.py
forge_sdk/protos/protos/consume_asset_pb2_grpc.py
forge_sdk/protos/protos/create_asset_pb2.py
forge_sdk/protos/protos/create_asset_pb2_grpc.py
forge_sdk/protos/protos/deactivate_protocol_pb2.py
forge_sdk/protos/protos/deactivate_protocol_pb2_grpc.py
forge_sdk/protos/protos/declare_pb2.py
forge_sdk/protos/protos/declare_pb2_grpc.py
forge_sdk/protos/protos/delegate_pb2.py
forge_sdk/protos/protos/delegate_pb2_grpc.py
forge_sdk/protos/protos/deposit_token_pb2.py
forge_sdk/protos/protos/deposit_token_pb2_grpc.py
forge_sdk/protos/protos/enum_pb2.py
forge_sdk/protos/protos/enum_pb2_grpc.py
forge_sdk/protos/protos/exchange_pb2.py
forge_sdk/protos/protos/exchange_pb2_grpc.py
forge_sdk/protos/protos/poke_pb2.py
forge_sdk/protos/protos/poke_pb2_grpc.py
forge_sdk/protos/protos/retrieve_swap_pb2.py
forge_sdk/protos/protos/retrieve_swap_pb2_grpc.py
forge_sdk/protos/protos/revoke_delegate_pb2.py
forge_sdk/protos/protos/revoke_delegate_pb2_grpc.py
forge_sdk/protos/protos/revoke_swap_pb2.py
forge_sdk/protos/protos/revoke_swap_pb2_grpc.py
forge_sdk/protos/protos/revoke_withdraw_pb2.py
forge_sdk/protos/protos/revoke_withdraw_pb2_grpc.py
forge_sdk/protos/protos/rpc_pb2.py
forge_python_sdk-0.39.0.dist-info/LICENSE
forge_python_sdk-0.39.0.dist-info/METADATA
forge_python_sdk-0.39.0.dist-info/WHEEL
forge_python_sdk-0.39.0.dist-info/top_level.txt
forge_python_sdk-0.39.0.dist-info/RECORD
