Metadata-Version: 2.1
Name: forge-python-sdk
Version: 0.39.0
Summary: A small example package
Home-page: https://github.com/ArcBlock/forge-python-sdk
Author: ArcBlock lnc
Author-email: riley@arcblock.io
License: UNKNOWN
Platform: UNKNOWN
Classifier: Programming Language :: Python :: 3
Classifier: License :: OSI Approved :: Apache Software License
Classifier: Operating System :: OS Independent
Requires-Dist: base58
Requires-Dist: grpcio
Requires-Dist: grpcio-tools
Requires-Dist: toml
Requires-Dist: deepmerge
Requires-Dist: pysha3
Requires-Dist: ed25519
Requires-Dist: secp256k1
Requires-Dist: pystache
Requires-Dist: requests
